jailmin/Bastille.py
jailmin/CmdConsole.py
jailmin/CmdList.py
jailmin/CmdUtil.py
jailmin/__init__.py
jailmin-0.0.3.dist-info/LICENSE
jailmin-0.0.3.dist-info/METADATA
jailmin-0.0.3.dist-info/WHEEL
jailmin-0.0.3.dist-info/entry_points.txt
jailmin-0.0.3.dist-info/top_level.txt
jailmin-0.0.3.dist-info/RECORD
