Metadata-Version: 2.1
Name: jailmin
Version: 0.0.3
Summary: Python wrapper to jail manager Bastille as a CLI enhancer.
Author-email: Ji-Haw Foo <jhfoo@kungfoo.info>
Project-URL: Homepage, https://github.com/jhfoo/jailmin
Keywords: bastille,freebsd,jail
License-File: LICENSE
